{
  "schemaVersion": 1,
  "id": "way_much_faster_oxidize_reborn",
  "version": "${version}",

  "name": "Way Much Faster Oxidize Reborn",
  "description": "Just place copper next to water, or pour water on copper.",
  "authors": [
    "Jayden215",
    "MarbleGateKeeper (Original Creator)"
  ],
  "contact": {
    "sources": "https://github.com/jayden315/WayMuchFasterOxidizeReborn"
  },

  "license": "MIT",
  "icon": "assets/wmfo_reload/icon.png",
  "environment": "*",
  "entrypoints": {
    "main": [
      "com.jayden215.wmfo_reload.Faster"
    ]
  },
  "mixins": [
    "way_much_faster_oxidize_reborn.mixins.json"
  ],

  "depends": {
    "fabricloader": "0.15.7",
    "fabric": "*",
    "minecraft": "*",
    "java": ">=17"
  }
}